<?xml version="1.0" encoding="utf-8"?>
<TextureAtlas imagePath="botfriend_playable.png">
	<!-- Created with Adobe Animate version 21.0.3.38773 -->
	<!-- http://www.adobe.com/products/animate.html -->
	<SubTexture name="danceleft0000" x="0" y="0" width="393" height="476" frameX="-5" frameY="0" frameWidth="398" frameHeight="478"/>
	<SubTexture name="danceleft0001" x="0" y="0" width="393" height="476" frameX="-5" frameY="0" frameWidth="398" frameHeight="478"/>
	<SubTexture name="danceleft0002" x="413" y="0" width="395" height="445" frameX="0" frameY="-33" frameWidth="398" frameHeight="478"/>
	<SubTexture name="danceleft0003" x="413" y="0" width="395" height="445" frameX="0" frameY="-33" frameWidth="398" frameHeight="478"/>
	<SubTexture name="danceleft0004" x="828" y="0" width="396" height="460" frameX="0" frameY="-18" frameWidth="398" frameHeight="478"/>
	<SubTexture name="danceleft0005" x="828" y="0" width="396" height="460" frameX="0" frameY="-18" frameWidth="398" frameHeight="478"/>
	<SubTexture name="danceleft0006" x="1244" y="0" width="396" height="460" frameX="0" frameY="-18" frameWidth="398" frameHeight="478"/>
	<SubTexture name="danceleft0007" x="1244" y="0" width="396" height="460" frameX="0" frameY="-18" frameWidth="398" frameHeight="478"/>
	<SubTexture name="danceleft0008" x="1244" y="0" width="396" height="460" frameX="0" frameY="-18" frameWidth="398" frameHeight="478"/>
	<SubTexture name="danceleft0009" x="1244" y="0" width="396" height="460" frameX="0" frameY="-18" frameWidth="398" frameHeight="478"/>
	<SubTexture name="danceleft0010" x="1244" y="0" width="396" height="460" frameX="0" frameY="-18" frameWidth="398" frameHeight="478"/>
	<SubTexture name="danceleft0011" x="1244" y="0" width="396" height="460" frameX="0" frameY="-18" frameWidth="398" frameHeight="478"/>
	<SubTexture name="danceleft0012" x="1244" y="0" width="396" height="460" frameX="0" frameY="-18" frameWidth="398" frameHeight="478"/>
	<SubTexture name="danceleft0013" x="1244" y="0" width="396" height="460" frameX="0" frameY="-18" frameWidth="398" frameHeight="478"/>
	<SubTexture name="danceright0000" x="1660" y="0" width="390" height="485" frameX="-3" frameY="-2" frameWidth="397" frameHeight="487"/>
	<SubTexture name="danceright0001" x="1660" y="0" width="390" height="485" frameX="-3" frameY="-2" frameWidth="397" frameHeight="487"/>
	<SubTexture name="danceright0002" x="2070" y="0" width="396" height="485" frameX="-1" frameY="0" frameWidth="397" frameHeight="487"/>
	<SubTexture name="danceright0003" x="2070" y="0" width="396" height="485" frameX="-1" frameY="0" frameWidth="397" frameHeight="487"/>
	<SubTexture name="danceright0004" x="2486" y="0" width="397" height="476" frameX="0" frameY="-9" frameWidth="397" frameHeight="487"/>
	<SubTexture name="danceright0005" x="2486" y="0" width="397" height="476" frameX="0" frameY="-9" frameWidth="397" frameHeight="487"/>
	<SubTexture name="danceright0006" x="2903" y="0" width="397" height="478" frameX="0" frameY="-7" frameWidth="397" frameHeight="487"/>
	<SubTexture name="danceright0007" x="2903" y="0" width="397" height="478" frameX="0" frameY="-7" frameWidth="397" frameHeight="487"/>
	<SubTexture name="danceright0008" x="2903" y="0" width="397" height="478" frameX="0" frameY="-7" frameWidth="397" frameHeight="487"/>
	<SubTexture name="danceright0009" x="2903" y="0" width="397" height="478" frameX="0" frameY="-7" frameWidth="397" frameHeight="487"/>
	<SubTexture name="danceright0010" x="2903" y="0" width="397" height="478" frameX="0" frameY="-7" frameWidth="397" frameHeight="487"/>
	<SubTexture name="danceright0011" x="2903" y="0" width="397" height="478" frameX="0" frameY="-7" frameWidth="397" frameHeight="487"/>
	<SubTexture name="danceright0012" x="2903" y="0" width="397" height="478" frameX="0" frameY="-7" frameWidth="397" frameHeight="487"/>
	<SubTexture name="danceright0013" x="2903" y="0" width="397" height="478" frameX="0" frameY="-7" frameWidth="397" frameHeight="487"/>
	<SubTexture name="down0000" x="3320" y="0" width="382" height="409" frameX="-2" frameY="-24" frameWidth="384" frameHeight="433"/>
	<SubTexture name="down0001" x="3320" y="0" width="382" height="409" frameX="-2" frameY="-24" frameWidth="384" frameHeight="433"/>
	<SubTexture name="down0002" x="0" y="505" width="380" height="390" frameX="0" frameY="-43" frameWidth="384" frameHeight="433"/>
	<SubTexture name="down0003" x="0" y="505" width="380" height="390" frameX="0" frameY="-43" frameWidth="384" frameHeight="433"/>
	<SubTexture name="down0004" x="400" y="505" width="380" height="433" frameX="0" frameY="0" frameWidth="384" frameHeight="433"/>
	<SubTexture name="down0005" x="400" y="505" width="380" height="433" frameX="0" frameY="0" frameWidth="384" frameHeight="433"/>
	<SubTexture name="down0006" x="800" y="505" width="380" height="432" frameX="0" frameY="-1" frameWidth="384" frameHeight="433"/>
	<SubTexture name="down0007" x="800" y="505" width="380" height="432" frameX="0" frameY="-1" frameWidth="384" frameHeight="433"/>
	<SubTexture name="down0008" x="800" y="505" width="380" height="432" frameX="0" frameY="-1" frameWidth="384" frameHeight="433"/>
	<SubTexture name="down0009" x="800" y="505" width="380" height="432" frameX="0" frameY="-1" frameWidth="384" frameHeight="433"/>
	<SubTexture name="down0010" x="800" y="505" width="380" height="432" frameX="0" frameY="-1" frameWidth="384" frameHeight="433"/>
	<SubTexture name="down0011" x="800" y="505" width="380" height="432" frameX="0" frameY="-1" frameWidth="384" frameHeight="433"/>
	<SubTexture name="down0012" x="800" y="505" width="380" height="432" frameX="0" frameY="-1" frameWidth="384" frameHeight="433"/>
	<SubTexture name="down0013" x="800" y="505" width="380" height="432" frameX="0" frameY="-1" frameWidth="384" frameHeight="433"/>
	<SubTexture name="down0014" x="800" y="505" width="380" height="432" frameX="0" frameY="-1" frameWidth="384" frameHeight="433"/>
	<SubTexture name="down0015" x="800" y="505" width="380" height="432" frameX="0" frameY="-1" frameWidth="384" frameHeight="433"/>
	<SubTexture name="down0016" x="800" y="505" width="380" height="432" frameX="0" frameY="-1" frameWidth="384" frameHeight="433"/>
	<SubTexture name="down0017" x="800" y="505" width="380" height="432" frameX="0" frameY="-1" frameWidth="384" frameHeight="433"/>
	<SubTexture name="down0018" x="800" y="505" width="380" height="432" frameX="0" frameY="-1" frameWidth="384" frameHeight="433"/>
	<SubTexture name="down0019" x="800" y="505" width="380" height="432" frameX="0" frameY="-1" frameWidth="384" frameHeight="433"/>
	<SubTexture name="down0020" x="800" y="505" width="380" height="432" frameX="0" frameY="-1" frameWidth="384" frameHeight="433"/>
	<SubTexture name="down0021" x="800" y="505" width="380" height="432" frameX="0" frameY="-1" frameWidth="384" frameHeight="433"/>
	<SubTexture name="down0022" x="800" y="505" width="380" height="432" frameX="0" frameY="-1" frameWidth="384" frameHeight="433"/>
	<SubTexture name="down0023" x="800" y="505" width="380" height="432" frameX="0" frameY="-1" frameWidth="384" frameHeight="433"/>
	<SubTexture name="down0024" x="800" y="505" width="380" height="432" frameX="0" frameY="-1" frameWidth="384" frameHeight="433"/>
	<SubTexture name="down0025" x="800" y="505" width="380" height="432" frameX="0" frameY="-1" frameWidth="384" frameHeight="433"/>
	<SubTexture name="down0026" x="800" y="505" width="380" height="432" frameX="0" frameY="-1" frameWidth="384" frameHeight="433"/>
	<SubTexture name="down0027" x="800" y="505" width="380" height="432" frameX="0" frameY="-1" frameWidth="384" frameHeight="433"/>
	<SubTexture name="down0028" x="800" y="505" width="380" height="432" frameX="0" frameY="-1" frameWidth="384" frameHeight="433"/>
	<SubTexture name="down0029" x="800" y="505" width="380" height="432" frameX="0" frameY="-1" frameWidth="384" frameHeight="433"/>
	<SubTexture name="hey0000" x="1200" y="505" width="385" height="456" frameX="-1" frameY="-15" frameWidth="400" frameHeight="473"/>
	<SubTexture name="hey0001" x="1200" y="505" width="385" height="456" frameX="-1" frameY="-15" frameWidth="400" frameHeight="473"/>
	<SubTexture name="hey0002" x="1605" y="505" width="399" height="469" frameX="0" frameY="-4" frameWidth="400" frameHeight="473"/>
	<SubTexture name="hey0003" x="1605" y="505" width="399" height="469" frameX="0" frameY="-4" frameWidth="400" frameHeight="473"/>
	<SubTexture name="hey0004" x="2024" y="505" width="400" height="472" frameX="0" frameY="-1" frameWidth="400" frameHeight="473"/>
	<SubTexture name="hey0005" x="2024" y="505" width="400" height="472" frameX="0" frameY="-1" frameWidth="400" frameHeight="473"/>
	<SubTexture name="hey0006" x="2444" y="505" width="400" height="473"/>
	<SubTexture name="hey0007" x="2444" y="505" width="400" height="473"/>
	<SubTexture name="hey0008" x="2444" y="505" width="400" height="473"/>
	<SubTexture name="hey0009" x="2444" y="505" width="400" height="473"/>
	<SubTexture name="hey0010" x="2444" y="505" width="400" height="473"/>
	<SubTexture name="hey0011" x="2444" y="505" width="400" height="473"/>
	<SubTexture name="hey0012" x="2444" y="505" width="400" height="473"/>
	<SubTexture name="hey0013" x="2444" y="505" width="400" height="473"/>
	<SubTexture name="hey0014" x="2444" y="505" width="400" height="473"/>
	<SubTexture name="hey0015" x="2444" y="505" width="400" height="473"/>
	<SubTexture name="hey0016" x="2444" y="505" width="400" height="473"/>
	<SubTexture name="hey0017" x="2444" y="505" width="400" height="473"/>
	<SubTexture name="hey0018" x="2444" y="505" width="400" height="473"/>
	<SubTexture name="hey0019" x="2444" y="505" width="400" height="473"/>
	<SubTexture name="hey0020" x="2444" y="505" width="400" height="473"/>
	<SubTexture name="hey0021" x="2444" y="505" width="400" height="473"/>
	<SubTexture name="hey0022" x="2444" y="505" width="400" height="473"/>
	<SubTexture name="hey0023" x="2444" y="505" width="400" height="473"/>
	<SubTexture name="hey0024" x="2444" y="505" width="400" height="473"/>
	<SubTexture name="hey0025" x="2444" y="505" width="400" height="473"/>
	<SubTexture name="left0000" x="2864" y="505" width="397" height="436" frameX="0" frameY="-29" frameWidth="398" frameHeight="465"/>
	<SubTexture name="left0001" x="2864" y="505" width="397" height="436" frameX="0" frameY="-29" frameWidth="398" frameHeight="465"/>
	<SubTexture name="left0002" x="3281" y="505" width="390" height="449" frameX="-8" frameY="-16" frameWidth="398" frameHeight="465"/>
	<SubTexture name="left0003" x="3281" y="505" width="390" height="449" frameX="-8" frameY="-16" frameWidth="398" frameHeight="465"/>
	<SubTexture name="left0004" x="3691" y="505" width="390" height="465" frameX="-8" frameY="0" frameWidth="398" frameHeight="465"/>
	<SubTexture name="left0005" x="3691" y="505" width="390" height="465" frameX="-8" frameY="0" frameWidth="398" frameHeight="465"/>
	<SubTexture name="left0006" x="0" y="998" width="390" height="463" frameX="-8" frameY="-2" frameWidth="398" frameHeight="465"/>
	<SubTexture name="left0007" x="0" y="998" width="390" height="463" frameX="-8" frameY="-2" frameWidth="398" frameHeight="465"/>
	<SubTexture name="left0008" x="0" y="998" width="390" height="463" frameX="-8" frameY="-2" frameWidth="398" frameHeight="465"/>
	<SubTexture name="left0009" x="0" y="998" width="390" height="463" frameX="-8" frameY="-2" frameWidth="398" frameHeight="465"/>
	<SubTexture name="left0010" x="0" y="998" width="390" height="463" frameX="-8" frameY="-2" frameWidth="398" frameHeight="465"/>
	<SubTexture name="left0011" x="0" y="998" width="390" height="463" frameX="-8" frameY="-2" frameWidth="398" frameHeight="465"/>
	<SubTexture name="left0012" x="0" y="998" width="390" height="463" frameX="-8" frameY="-2" frameWidth="398" frameHeight="465"/>
	<SubTexture name="left0013" x="0" y="998" width="390" height="463" frameX="-8" frameY="-2" frameWidth="398" frameHeight="465"/>
	<SubTexture name="left0014" x="0" y="998" width="390" height="463" frameX="-8" frameY="-2" frameWidth="398" frameHeight="465"/>
	<SubTexture name="missleft0000" x="2864" y="505" width="397" height="436" frameX="0" frameY="-35" frameWidth="398" frameHeight="465"/>
	<SubTexture name="missleft0001" x="410" y="998" width="392" height="468" frameX="-3" frameY="0" frameWidth="397" frameHeight="471"/>
	<SubTexture name="missleft0002" x="410" y="998" width="392" height="468" frameX="-3" frameY="0" frameWidth="397" frameHeight="471"/>
	<SubTexture name="missleft0003" x="822" y="998" width="395" height="468" frameX="0" frameY="0" frameWidth="397" frameHeight="471"/>
	<SubTexture name="missleft0004" x="822" y="998" width="395" height="468" frameX="0" frameY="0" frameWidth="397" frameHeight="471"/>
	<SubTexture name="missleft0005" x="822" y="998" width="395" height="468" frameX="0" frameY="0" frameWidth="397" frameHeight="471"/>
	<SubTexture name="missleft0006" x="822" y="998" width="395" height="468" frameX="0" frameY="0" frameWidth="397" frameHeight="471"/>
	<SubTexture name="missleft0007" x="822" y="998" width="395" height="468" frameX="0" frameY="0" frameWidth="397" frameHeight="471"/>
	<SubTexture name="missleft0008" x="822" y="998" width="395" height="468" frameX="0" frameY="0" frameWidth="397" frameHeight="471"/>
	<SubTexture name="missleft0009" x="822" y="998" width="395" height="468" frameX="0" frameY="0" frameWidth="397" frameHeight="471"/>
	<SubTexture name="missleft0010" x="822" y="998" width="395" height="468" frameX="0" frameY="0" frameWidth="397" frameHeight="471"/>
	<SubTexture name="missleft0011" x="822" y="998" width="395" height="468" frameX="0" frameY="0" frameWidth="397" frameHeight="471"/>
	<SubTexture name="missleft0012" x="822" y="998" width="395" height="468" frameX="0" frameY="0" frameWidth="397" frameHeight="471"/>
	<SubTexture name="missleft0013" x="822" y="998" width="395" height="468" frameX="0" frameY="0" frameWidth="397" frameHeight="471"/>
	<SubTexture name="missleft0014" x="822" y="998" width="395" height="468" frameX="0" frameY="0" frameWidth="397" frameHeight="471"/>
	<SubTexture name="missleft0015" x="822" y="998" width="395" height="468" frameX="0" frameY="0" frameWidth="397" frameHeight="471"/>
	<SubTexture name="missleft0016" x="822" y="998" width="395" height="468" frameX="0" frameY="0" frameWidth="397" frameHeight="471"/>
	<SubTexture name="missleft0017" x="822" y="998" width="395" height="468" frameX="0" frameY="0" frameWidth="397" frameHeight="471"/>
	<SubTexture name="missleft0018" x="822" y="998" width="395" height="468" frameX="0" frameY="0" frameWidth="397" frameHeight="471"/>
	<SubTexture name="missleft0019" x="822" y="998" width="395" height="468" frameX="0" frameY="0" frameWidth="397" frameHeight="471"/>
	<SubTexture name="missleft0020" x="822" y="998" width="395" height="468" frameX="0" frameY="0" frameWidth="397" frameHeight="471"/>
	<SubTexture name="missleft0021" x="822" y="998" width="395" height="468" frameX="0" frameY="0" frameWidth="397" frameHeight="471"/>
	<SubTexture name="missleft0022" x="822" y="998" width="395" height="468" frameX="0" frameY="0" frameWidth="397" frameHeight="471"/>
	<SubTexture name="missleft0023" x="822" y="998" width="395" height="468" frameX="0" frameY="0" frameWidth="397" frameHeight="471"/>
	<SubTexture name="missleft0024" x="822" y="998" width="395" height="468" frameX="0" frameY="0" frameWidth="397" frameHeight="471"/>
	<SubTexture name="missleft0025" x="822" y="998" width="395" height="468" frameX="0" frameY="0" frameWidth="397" frameHeight="471"/>
	<SubTexture name="missleft0026" x="822" y="998" width="395" height="468" frameX="0" frameY="0" frameWidth="397" frameHeight="471"/>
	<SubTexture name="missleft0027" x="822" y="998" width="395" height="468" frameX="0" frameY="0" frameWidth="397" frameHeight="471"/>
	<SubTexture name="missleft0028" x="822" y="998" width="395" height="468" frameX="0" frameY="0" frameWidth="397" frameHeight="471"/>
	<SubTexture name="missleft0029" x="822" y="998" width="395" height="468" frameX="0" frameY="0" frameWidth="397" frameHeight="471"/>
	<SubTexture name="missleft0030" x="822" y="998" width="395" height="468" frameX="0" frameY="0" frameWidth="397" frameHeight="471"/>
	<SubTexture name="missleft0031" x="822" y="998" width="395" height="468" frameX="0" frameY="0" frameWidth="397" frameHeight="471"/>
	<SubTexture name="missleft0032" x="822" y="998" width="395" height="468" frameX="0" frameY="0" frameWidth="397" frameHeight="471"/>
	<SubTexture name="missleft0033" x="822" y="998" width="395" height="468" frameX="0" frameY="0" frameWidth="397" frameHeight="471"/>
	<SubTexture name="missright0000" x="3223" y="998" width="400" height="441" frameX="-4" frameY="0" frameWidth="403" frameHeight="476"/>
	<SubTexture name="missright0001" x="1237" y="998" width="399" height="434" frameX="0" frameY="-5" frameWidth="405" frameHeight="441"/>
	<SubTexture name="missright0002" x="1237" y="998" width="399" height="434" frameX="0" frameY="-5" frameWidth="405" frameHeight="441"/>
	<SubTexture name="missright0003" x="1656" y="998" width="401" height="434" frameX="-4" frameY="-5" frameWidth="405" frameHeight="441"/>
	<SubTexture name="missright0004" x="1656" y="998" width="401" height="434" frameX="-4" frameY="-5" frameWidth="405" frameHeight="441"/>
	<SubTexture name="missright0005" x="1656" y="998" width="401" height="434" frameX="-4" frameY="-5" frameWidth="405" frameHeight="441"/>
	<SubTexture name="missright0006" x="1656" y="998" width="401" height="434" frameX="-4" frameY="-5" frameWidth="405" frameHeight="441"/>
	<SubTexture name="missright0007" x="1656" y="998" width="401" height="434" frameX="-4" frameY="-5" frameWidth="405" frameHeight="441"/>
	<SubTexture name="missright0008" x="1656" y="998" width="401" height="434" frameX="-4" frameY="-5" frameWidth="405" frameHeight="441"/>
	<SubTexture name="missright0009" x="1656" y="998" width="401" height="434" frameX="-4" frameY="-5" frameWidth="405" frameHeight="441"/>
	<SubTexture name="missright0010" x="1656" y="998" width="401" height="434" frameX="-4" frameY="-5" frameWidth="405" frameHeight="441"/>
	<SubTexture name="missright0011" x="1656" y="998" width="401" height="434" frameX="-4" frameY="-5" frameWidth="405" frameHeight="441"/>
	<SubTexture name="missright0012" x="1656" y="998" width="401" height="434" frameX="-4" frameY="-5" frameWidth="405" frameHeight="441"/>
	<SubTexture name="missright0013" x="1656" y="998" width="401" height="434" frameX="-4" frameY="-5" frameWidth="405" frameHeight="441"/>
	<SubTexture name="missright0014" x="1656" y="998" width="401" height="434" frameX="-4" frameY="-5" frameWidth="405" frameHeight="441"/>
	<SubTexture name="missright0015" x="1656" y="998" width="401" height="434" frameX="-4" frameY="-5" frameWidth="405" frameHeight="441"/>
	<SubTexture name="missright0016" x="1656" y="998" width="401" height="434" frameX="-4" frameY="-5" frameWidth="405" frameHeight="441"/>
	<SubTexture name="missright0017" x="1656" y="998" width="401" height="434" frameX="-4" frameY="-5" frameWidth="405" frameHeight="441"/>
	<SubTexture name="missright0018" x="1656" y="998" width="401" height="434" frameX="-4" frameY="-5" frameWidth="405" frameHeight="441"/>
	<SubTexture name="missright0019" x="1656" y="998" width="401" height="434" frameX="-4" frameY="-5" frameWidth="405" frameHeight="441"/>
	<SubTexture name="missright0020" x="1656" y="998" width="401" height="434" frameX="-4" frameY="-5" frameWidth="405" frameHeight="441"/>
	<SubTexture name="missright0021" x="1656" y="998" width="401" height="434" frameX="-4" frameY="-5" frameWidth="405" frameHeight="441"/>
	<SubTexture name="missright0022" x="1656" y="998" width="401" height="434" frameX="-4" frameY="-5" frameWidth="405" frameHeight="441"/>
	<SubTexture name="missright0023" x="1656" y="998" width="401" height="434" frameX="-4" frameY="-5" frameWidth="405" frameHeight="441"/>
	<SubTexture name="missright0024" x="1656" y="998" width="401" height="434" frameX="-4" frameY="-5" frameWidth="405" frameHeight="441"/>
	<SubTexture name="missright0025" x="1656" y="998" width="401" height="434" frameX="-4" frameY="-5" frameWidth="405" frameHeight="441"/>
	<SubTexture name="missright0026" x="1656" y="998" width="401" height="434" frameX="-4" frameY="-5" frameWidth="405" frameHeight="441"/>
	<SubTexture name="missright0027" x="1656" y="998" width="401" height="434" frameX="-4" frameY="-5" frameWidth="405" frameHeight="441"/>
	<SubTexture name="missright0028" x="1656" y="998" width="401" height="434" frameX="-4" frameY="-5" frameWidth="405" frameHeight="441"/>
	<SubTexture name="missright0029" x="1656" y="998" width="401" height="434" frameX="-4" frameY="-5" frameWidth="405" frameHeight="441"/>
	<SubTexture name="missright0030" x="1656" y="998" width="401" height="434" frameX="-4" frameY="-5" frameWidth="405" frameHeight="441"/>
	<SubTexture name="missright0031" x="1656" y="998" width="401" height="434" frameX="-4" frameY="-5" frameWidth="405" frameHeight="441"/>
	<SubTexture name="missright0032" x="1656" y="998" width="401" height="434" frameX="-4" frameY="-5" frameWidth="405" frameHeight="441"/>
	<SubTexture name="missright0033" x="1656" y="998" width="401" height="434" frameX="-4" frameY="-5" frameWidth="405" frameHeight="441"/>
	<SubTexture name="missright0034" x="1656" y="998" width="401" height="434" frameX="-4" frameY="-5" frameWidth="405" frameHeight="441"/>
	<SubTexture name="missright0035" x="1656" y="998" width="401" height="434" frameX="-4" frameY="-5" frameWidth="405" frameHeight="441"/>
	<SubTexture name="missright0036" x="1656" y="998" width="401" height="434" frameX="-4" frameY="-5" frameWidth="405" frameHeight="441"/>
	<SubTexture name="missright0037" x="1656" y="998" width="401" height="434" frameX="-4" frameY="-5" frameWidth="405" frameHeight="441"/>
	<SubTexture name="missright0038" x="1656" y="998" width="401" height="434" frameX="-4" frameY="-5" frameWidth="405" frameHeight="441"/>
	<SubTexture name="missright0039" x="1656" y="998" width="401" height="434" frameX="-4" frameY="-5" frameWidth="405" frameHeight="441"/>
	<SubTexture name="missright0040" x="1656" y="998" width="401" height="434" frameX="-4" frameY="-5" frameWidth="405" frameHeight="441"/>
	<SubTexture name="missright0041" x="1656" y="998" width="401" height="434" frameX="-4" frameY="-5" frameWidth="405" frameHeight="441"/>
	<SubTexture name="missright0042" x="1656" y="998" width="401" height="434" frameX="-4" frameY="-5" frameWidth="405" frameHeight="441"/>
	<SubTexture name="missright0043" x="1656" y="998" width="401" height="434" frameX="-4" frameY="-5" frameWidth="405" frameHeight="441"/>
	<SubTexture name="missright0044" x="1656" y="998" width="401" height="434" frameX="-4" frameY="-5" frameWidth="405" frameHeight="441"/>
	<SubTexture name="missright0045" x="1656" y="998" width="401" height="434" frameX="-4" frameY="-5" frameWidth="405" frameHeight="441"/>
	<SubTexture name="missup0000" x="2077" y="998" width="360" height="463" frameX="-4" frameY="-42" frameWidth="365" frameHeight="505"/>
	<SubTexture name="missup0001" x="2457" y="998" width="365" height="499" frameX="0" frameY="-3" frameWidth="365" frameHeight="505"/>
	<SubTexture name="missup0002" x="2457" y="998" width="365" height="499" frameX="0" frameY="-3" frameWidth="365" frameHeight="505"/>
	<SubTexture name="missup0003" x="2842" y="998" width="361" height="502" frameX="-2" frameY="0" frameWidth="365" frameHeight="505"/>
	<SubTexture name="missup0004" x="2842" y="998" width="361" height="502" frameX="-2" frameY="0" frameWidth="365" frameHeight="505"/>
	<SubTexture name="missup0005" x="2842" y="998" width="361" height="502" frameX="-2" frameY="0" frameWidth="365" frameHeight="505"/>
	<SubTexture name="missup0006" x="2842" y="998" width="361" height="502" frameX="-2" frameY="0" frameWidth="365" frameHeight="505"/>
	<SubTexture name="missup0007" x="2842" y="998" width="361" height="502" frameX="-2" frameY="0" frameWidth="365" frameHeight="505"/>
	<SubTexture name="missup0008" x="2842" y="998" width="361" height="502" frameX="-2" frameY="0" frameWidth="365" frameHeight="505"/>
	<SubTexture name="missup0009" x="2842" y="998" width="361" height="502" frameX="-2" frameY="0" frameWidth="365" frameHeight="505"/>
	<SubTexture name="missup0010" x="2842" y="998" width="361" height="502" frameX="-2" frameY="0" frameWidth="365" frameHeight="505"/>
	<SubTexture name="missup0011" x="2842" y="998" width="361" height="502" frameX="-2" frameY="0" frameWidth="365" frameHeight="505"/>
	<SubTexture name="missup0012" x="2842" y="998" width="361" height="502" frameX="-2" frameY="0" frameWidth="365" frameHeight="505"/>
	<SubTexture name="missup0013" x="2842" y="998" width="361" height="502" frameX="-2" frameY="0" frameWidth="365" frameHeight="505"/>
	<SubTexture name="missup0014" x="2842" y="998" width="361" height="502" frameX="-2" frameY="0" frameWidth="365" frameHeight="505"/>
	<SubTexture name="missup0015" x="2842" y="998" width="361" height="502" frameX="-2" frameY="0" frameWidth="365" frameHeight="505"/>
	<SubTexture name="missup0016" x="2842" y="998" width="361" height="502" frameX="-2" frameY="0" frameWidth="365" frameHeight="505"/>
	<SubTexture name="missup0017" x="2842" y="998" width="361" height="502" frameX="-2" frameY="0" frameWidth="365" frameHeight="505"/>
	<SubTexture name="missup0018" x="2842" y="998" width="361" height="502" frameX="-2" frameY="0" frameWidth="365" frameHeight="505"/>
	<SubTexture name="missup0019" x="2842" y="998" width="361" height="502" frameX="-2" frameY="0" frameWidth="365" frameHeight="505"/>
	<SubTexture name="missup0020" x="2842" y="998" width="361" height="502" frameX="-2" frameY="0" frameWidth="365" frameHeight="505"/>
	<SubTexture name="missup0021" x="2842" y="998" width="361" height="502" frameX="-2" frameY="0" frameWidth="365" frameHeight="505"/>
	<SubTexture name="missup0022" x="2842" y="998" width="361" height="502" frameX="-2" frameY="0" frameWidth="365" frameHeight="505"/>
	<SubTexture name="missup0023" x="2842" y="998" width="361" height="502" frameX="-2" frameY="0" frameWidth="365" frameHeight="505"/>
	<SubTexture name="right0000" x="3223" y="998" width="400" height="441" frameX="-3" frameY="-35" frameWidth="403" frameHeight="476"/>
	<SubTexture name="right0001" x="3223" y="998" width="400" height="441" frameX="-3" frameY="-35" frameWidth="403" frameHeight="476"/>
	<SubTexture name="right0002" x="3643" y="998" width="400" height="476" frameX="0" frameY="0" frameWidth="403" frameHeight="476"/>
	<SubTexture name="right0003" x="3643" y="998" width="400" height="476" frameX="0" frameY="0" frameWidth="403" frameHeight="476"/>
	<SubTexture name="right0004" x="0" y="1520" width="400" height="472" frameX="0" frameY="-4" frameWidth="403" frameHeight="476"/>
	<SubTexture name="right0005" x="0" y="1520" width="400" height="472" frameX="0" frameY="-4" frameWidth="403" frameHeight="476"/>
	<SubTexture name="right0006" x="420" y="1520" width="400" height="475" frameX="0" frameY="-1" frameWidth="403" frameHeight="476"/>
	<SubTexture name="right0007" x="420" y="1520" width="400" height="475" frameX="0" frameY="-1" frameWidth="403" frameHeight="476"/>
	<SubTexture name="right0008" x="420" y="1520" width="400" height="475" frameX="0" frameY="-1" frameWidth="403" frameHeight="476"/>
	<SubTexture name="right0009" x="420" y="1520" width="400" height="475" frameX="0" frameY="-1" frameWidth="403" frameHeight="476"/>
	<SubTexture name="right0010" x="420" y="1520" width="400" height="475" frameX="0" frameY="-1" frameWidth="403" frameHeight="476"/>
	<SubTexture name="right0011" x="420" y="1520" width="400" height="475" frameX="0" frameY="-1" frameWidth="403" frameHeight="476"/>
	<SubTexture name="right0012" x="420" y="1520" width="400" height="475" frameX="0" frameY="-1" frameWidth="403" frameHeight="476"/>
	<SubTexture name="right0013" x="420" y="1520" width="400" height="475" frameX="0" frameY="-1" frameWidth="403" frameHeight="476"/>
	<SubTexture name="right0014" x="420" y="1520" width="400" height="475" frameX="0" frameY="-1" frameWidth="403" frameHeight="476"/>
	<SubTexture name="right0015" x="420" y="1520" width="400" height="475" frameX="0" frameY="-1" frameWidth="403" frameHeight="476"/>
	<SubTexture name="right0016" x="420" y="1520" width="400" height="475" frameX="0" frameY="-1" frameWidth="403" frameHeight="476"/>
	<SubTexture name="right0017" x="420" y="1520" width="400" height="475" frameX="0" frameY="-1" frameWidth="403" frameHeight="476"/>
	<SubTexture name="right0018" x="420" y="1520" width="400" height="475" frameX="0" frameY="-1" frameWidth="403" frameHeight="476"/>
	<SubTexture name="right0019" x="420" y="1520" width="400" height="475" frameX="0" frameY="-1" frameWidth="403" frameHeight="476"/>
	<SubTexture name="right0020" x="420" y="1520" width="400" height="475" frameX="0" frameY="-1" frameWidth="403" frameHeight="476"/>
	<SubTexture name="right0021" x="420" y="1520" width="400" height="475" frameX="0" frameY="-1" frameWidth="403" frameHeight="476"/>
	<SubTexture name="right0022" x="420" y="1520" width="400" height="475" frameX="0" frameY="-1" frameWidth="403" frameHeight="476"/>
	<SubTexture name="right0023" x="420" y="1520" width="400" height="475" frameX="0" frameY="-1" frameWidth="403" frameHeight="476"/>
	<SubTexture name="right0024" x="420" y="1520" width="400" height="475" frameX="0" frameY="-1" frameWidth="403" frameHeight="476"/>
	<SubTexture name="right0025" x="420" y="1520" width="400" height="475" frameX="0" frameY="-1" frameWidth="403" frameHeight="476"/>
	<SubTexture name="right0026" x="420" y="1520" width="400" height="475" frameX="0" frameY="-1" frameWidth="403" frameHeight="476"/>
	<SubTexture name="right0027" x="420" y="1520" width="400" height="475" frameX="0" frameY="-1" frameWidth="403" frameHeight="476"/>
	<SubTexture name="right0028" x="420" y="1520" width="400" height="475" frameX="0" frameY="-1" frameWidth="403" frameHeight="476"/>
	<SubTexture name="right0029" x="420" y="1520" width="400" height="475" frameX="0" frameY="-1" frameWidth="403" frameHeight="476"/>
	<SubTexture name="right0030" x="420" y="1520" width="400" height="475" frameX="0" frameY="-1" frameWidth="403" frameHeight="476"/>
	<SubTexture name="right0031" x="420" y="1520" width="400" height="475" frameX="0" frameY="-1" frameWidth="403" frameHeight="476"/>
	<SubTexture name="right0032" x="420" y="1520" width="400" height="475" frameX="0" frameY="-1" frameWidth="403" frameHeight="476"/>
	<SubTexture name="right0033" x="420" y="1520" width="400" height="475" frameX="0" frameY="-1" frameWidth="403" frameHeight="476"/>
	<SubTexture name="right0034" x="420" y="1520" width="400" height="475" frameX="0" frameY="-1" frameWidth="403" frameHeight="476"/>
	<SubTexture name="right0035" x="420" y="1520" width="400" height="475" frameX="0" frameY="-1" frameWidth="403" frameHeight="476"/>
	<SubTexture name="right0036" x="420" y="1520" width="400" height="475" frameX="0" frameY="-1" frameWidth="403" frameHeight="476"/>
	<SubTexture name="right0037" x="420" y="1520" width="400" height="475" frameX="0" frameY="-1" frameWidth="403" frameHeight="476"/>
	<SubTexture name="right0038" x="420" y="1520" width="400" height="475" frameX="0" frameY="-1" frameWidth="403" frameHeight="476"/>
	<SubTexture name="right0039" x="420" y="1520" width="400" height="475" frameX="0" frameY="-1" frameWidth="403" frameHeight="476"/>
	<SubTexture name="right0040" x="420" y="1520" width="400" height="475" frameX="0" frameY="-1" frameWidth="403" frameHeight="476"/>
	<SubTexture name="right0041" x="420" y="1520" width="400" height="475" frameX="0" frameY="-1" frameWidth="403" frameHeight="476"/>
	<SubTexture name="right0042" x="420" y="1520" width="400" height="475" frameX="0" frameY="-1" frameWidth="403" frameHeight="476"/>
	<SubTexture name="right0043" x="420" y="1520" width="400" height="475" frameX="0" frameY="-1" frameWidth="403" frameHeight="476"/>
	<SubTexture name="right0044" x="420" y="1520" width="400" height="475" frameX="0" frameY="-1" frameWidth="403" frameHeight="476"/>
	<SubTexture name="right0045" x="420" y="1520" width="400" height="475" frameX="0" frameY="-1" frameWidth="403" frameHeight="476"/>
	<SubTexture name="right0046" x="420" y="1520" width="400" height="475" frameX="0" frameY="-1" frameWidth="403" frameHeight="476"/>
	<SubTexture name="right0047" x="420" y="1520" width="400" height="475" frameX="0" frameY="-1" frameWidth="403" frameHeight="476"/>
	<SubTexture name="right0048" x="420" y="1520" width="400" height="475" frameX="0" frameY="-1" frameWidth="403" frameHeight="476"/>
	<SubTexture name="right0049" x="420" y="1520" width="400" height="475" frameX="0" frameY="-1" frameWidth="403" frameHeight="476"/>
	<SubTexture name="right0050" x="420" y="1520" width="400" height="475" frameX="0" frameY="-1" frameWidth="403" frameHeight="476"/>
	<SubTexture name="right0051" x="420" y="1520" width="400" height="475" frameX="0" frameY="-1" frameWidth="403" frameHeight="476"/>
	<SubTexture name="right0052" x="420" y="1520" width="400" height="475" frameX="0" frameY="-1" frameWidth="403" frameHeight="476"/>
	<SubTexture name="right0053" x="420" y="1520" width="400" height="475" frameX="0" frameY="-1" frameWidth="403" frameHeight="476"/>
	<SubTexture name="right0054" x="420" y="1520" width="400" height="475" frameX="0" frameY="-1" frameWidth="403" frameHeight="476"/>
	<SubTexture name="right0055" x="420" y="1520" width="400" height="475" frameX="0" frameY="-1" frameWidth="403" frameHeight="476"/>
	<SubTexture name="right0056" x="420" y="1520" width="400" height="475" frameX="0" frameY="-1" frameWidth="403" frameHeight="476"/>
	<SubTexture name="right0057" x="420" y="1520" width="400" height="475" frameX="0" frameY="-1" frameWidth="403" frameHeight="476"/>
	<SubTexture name="right0058" x="420" y="1520" width="400" height="475" frameX="0" frameY="-1" frameWidth="403" frameHeight="476"/>
	<SubTexture name="right0059" x="420" y="1520" width="400" height="475" frameX="0" frameY="-1" frameWidth="403" frameHeight="476"/>
	<SubTexture name="right0060" x="420" y="1520" width="400" height="475" frameX="0" frameY="-1" frameWidth="403" frameHeight="476"/>
	<SubTexture name="right0061" x="420" y="1520" width="400" height="475" frameX="0" frameY="-1" frameWidth="403" frameHeight="476"/>
	<SubTexture name="up0000" x="840" y="1520" width="360" height="463" frameX="-7" frameY="-12" frameWidth="408" frameHeight="475"/>
	<SubTexture name="up0001" x="840" y="1520" width="360" height="463" frameX="-7" frameY="-12" frameWidth="408" frameHeight="475"/>
	<SubTexture name="up0002" x="1220" y="1520" width="408" height="448" frameX="0" frameY="-26" frameWidth="408" frameHeight="475"/>
	<SubTexture name="up0003" x="1220" y="1520" width="408" height="448" frameX="0" frameY="-26" frameWidth="408" frameHeight="475"/>
	<SubTexture name="up0004" x="1648" y="1520" width="369" height="474" frameX="0" frameY="0" frameWidth="408" frameHeight="475"/>
	<SubTexture name="up0005" x="1648" y="1520" width="369" height="474" frameX="0" frameY="0" frameWidth="408" frameHeight="475"/>
	<SubTexture name="up0006" x="2037" y="1520" width="369" height="469" frameX="0" frameY="-5" frameWidth="408" frameHeight="475"/>
	<SubTexture name="up0007" x="2037" y="1520" width="369" height="469" frameX="0" frameY="-5" frameWidth="408" frameHeight="475"/>
	<SubTexture name="up0008" x="2037" y="1520" width="369" height="469" frameX="0" frameY="-5" frameWidth="408" frameHeight="475"/>
	<SubTexture name="up0009" x="2037" y="1520" width="369" height="469" frameX="0" frameY="-5" frameWidth="408" frameHeight="475"/>
	<SubTexture name="up0010" x="2037" y="1520" width="369" height="469" frameX="0" frameY="-5" frameWidth="408" frameHeight="475"/>
	<SubTexture name="up0011" x="2037" y="1520" width="369" height="469" frameX="0" frameY="-5" frameWidth="408" frameHeight="475"/>
	<SubTexture name="up0012" x="2037" y="1520" width="369" height="469" frameX="0" frameY="-5" frameWidth="408" frameHeight="475"/>
	<SubTexture name="up0013" x="2037" y="1520" width="369" height="469" frameX="0" frameY="-5" frameWidth="408" frameHeight="475"/>
	<SubTexture name="up0014" x="2037" y="1520" width="369" height="469" frameX="0" frameY="-5" frameWidth="408" frameHeight="475"/>
</TextureAtlas>
